forteenall_kit/__init__.py
forteenall_kit/feature.py
forteenall_kit/invoke.py
forteenall_kit/models.py
forteenall_kit/invokers/__init__.py
forteenall_kit/invokers/djangoModel.py
forteenall_kit/invokers/django_from_usecreatefunc.py
forteenall_kit/invokers/django_model_viewset.py
forteenall_kit/invokers/django_simple_CRUD.py
forteenall_kit/invokers/django_start_app.py
forteenall_kit/invokers/django_start_project.py
forteenall_kit/invokers/django_url_add.py
forteenall_kit/invokers/flow_ask.py
forteenall_kit/invokers/flow_wbs.py
forteenall_kit/invokers/forteenall_ping.py
forteenall_kit/invokers/nextjs_create_hooks.py
forteenall_kit/invokers/nextjs_header.py
forteenall_kit/invokers/nextjs_hero_component.py
forteenall_kit/invokers/nextjs_home_page.py
forteenall_kit/invokers/nextjs_layout_create.py
forteenall_kit/invokers/nextjs_link_button.py
forteenall_kit/invokers/nextjs_list_content.py
forteenall_kit/invokers/nextjs_page_create.py
forteenall_kit/invokers/nextjs_use_hooks.py
forteenall_kit/invokers/spaceDup.py
forteenall_kit/utils/__init__.py
forteenall_kit/utils/core.py
forteenall_kit/utils/html.py
forteenall_kit/utils/python.py
forteenall_kit/utils/react.py
forteenall_kit-0.1.79.dist-info/licenses/LICENSE
forteenall_kit-0.1.79.dist-info/METADATA
forteenall_kit-0.1.79.dist-info/WHEEL
forteenall_kit-0.1.79.dist-info/top_level.txt
forteenall_kit-0.1.79.dist-info/RECORD
