Metadata-Version: 2.4
Name: forteenall_kit
Version: 0.1.79
Summary: A kit for developing a project
Home-page: https://github.com/algonouir/forteenall_kit
Author: Mahdi Nouri
Author-email: Mahdi Nouri <algo.mahdi.nouri@gmail.com>
License:                     GNU GENERAL PUBLIC LICENSE
Classifier: Programming Language :: Python :: 3
Classifier: Operating System :: OS Independent
Requires-Python: >=3.10
License-File: LICENSE
Dynamic: author
Dynamic: home-page
Dynamic: license-file
